drunk_santa/__init__.py
drunk_santa/beer.py
drunk_santa/client.py
drunk_santa/config.py
drunk_santa-0.0.3.dist-info/LICENSE
drunk_santa-0.0.3.dist-info/METADATA
drunk_santa-0.0.3.dist-info/WHEEL
drunk_santa-0.0.3.dist-info/top_level.txt
drunk_santa-0.0.3.dist-info/RECORD
