Metadata-Version: 2.1
Name: drunk-santa
Version: 0.0.3
Summary: A package for beer extraction. Have fun!
Author-email: Alexandru Lupei <lupei.alexandru2001@gmail.com>
License: MIT License        
Project-URL: Homepage, https://github.com/pypa/sampleproject
Project-URL: Bug Tracker, https://github.com/pypa/sampleproject/issues
Classifier: Programming Language :: Python :: 3
Classifier: License :: OSI Approved :: MIT License
Classifier: Operating System :: OS Independent
Requires-Python: >=3.7
License-File: LICENSE
Requires-Dist: requests (==2.28.1)
